my_turing_calc/__init__.py
my_turing_calc/calc.py
martin_macak_calculator_test-0.0.1.dist-info/METADATA
martin_macak_calculator_test-0.0.1.dist-info/WHEEL
martin_macak_calculator_test-0.0.1.dist-info/top_level.txt
martin_macak_calculator_test-0.0.1.dist-info/RECORD
