Metadata-Version: 2.1
Name: martin-macak-calculator-test
Version: 0.0.1
Summary: This is test calculator for my Turing College project
Author: NeuralNine (Florian Dedov)
Author-email: <mail@neuralnine.com>
Keywords: python,calculator,learning,turing college
Classifier: Development Status :: 1 - Planning
Classifier: Intended Audience :: Developers
Classifier: Programming Language :: Python :: 3
Classifier: Operating System :: Unix
Classifier: Operating System :: MacOS :: MacOS X
Classifier: Operating System :: Microsoft :: Windows
